opendata/__init__.py
opendata/renfe/__init__.py
opendata/spanish_rail_tickets/__init__.py
gurus_opendata-0.0.2.dist-info/LICENSE
gurus_opendata-0.0.2.dist-info/METADATA
gurus_opendata-0.0.2.dist-info/WHEEL
gurus_opendata-0.0.2.dist-info/top_level.txt
gurus_opendata-0.0.2.dist-info/RECORD
