Metadata-Version: 2.1
Name: gurus-opendata
Version: 0.0.2
Summary: We get Data from the Internet and We make it available to the World
Home-page: https://github.com/TheGurus/opendata
Author: The Gurus
Author-email: opendata@thegurus.tech
License: UNKNOWN
Platform: UNKNOWN
Classifier: Programming Language :: Python :: 3
Classifier: License :: OSI Approved :: MIT License
Classifier: Operating System :: OS Independent
Requires-Python: >=3.6
Requires-Dist: requests
